rtl/sleep_controller.v
`timescale 1ns/1ps

module sleep_controller(

    input clk,
    input rst,

    input sleep_instruction,
    input wake_up,

    output reg sleep_mode

);

always @(posedge clk or posedge rst)
begin

    if(rst)
        sleep_mode <= 0;

    else if(wake_up)
        sleep_mode <= 0;

    else if(sleep_instruction)
        sleep_mode <= 1;

end

endmodule

rtl/control_unit.v
`timescale 1ns/1ps

module control_unit(

    input [3:0] opcode,

    output reg reg_write,
    output reg mem_read,
    output reg mem_write,
    output reg alu_src,
    output reg sleep

);

always @(*) begin

    reg_write = 0;
    mem_read  = 0;
    mem_write = 0;
    alu_src   = 0;
    sleep     = 0;

    case(opcode)

        4'b0000: reg_write = 1; // ADD
        4'b0001: reg_write = 1; // SUB
        4'b0010: reg_write = 1; // AND
        4'b0011: reg_write = 1; // OR
        4'b0100: reg_write = 1; // XOR

        4'b0101: begin
            mem_read  = 1;
            reg_write = 1;
        end

        4'b0110:
            mem_write = 1;

        4'b0111:
            reg_write = 1; // MAC

        4'b1001:
            sleep = 1;

    endcase

end

endmodule

rtl/instructon_memory.v
`timescale 1ns/1ps

module instruction_memory(

    input [3:0] address,
    output [15:0] instruction

);

reg [15:0] mem [0:15];

assign instruction = mem[address];

initial begin

    // ADD R0,R1,R2
    mem[0] = 16'b0000_00_01_10_000000;

    // SUB R1,R2,R3
    mem[1] = 16'b0001_01_10_11_000000;

    // MAC
    mem[2] = 16'b0111_00_01_10_000000;

    // SLEEP
    mem[3] = 16'b1001_000000000000;

    // NOP
    mem[4] = 16'b1111_000000000000;

end

endmodule

rtl/pc.v
`timescale 1ns/1ps

module pc(

    input clk,
    input rst,

    input stall,
    input sleep_mode,

    output reg [3:0] pc_out

);

always @(posedge clk or posedge rst)
begin

    if(rst)
        pc_out <= 4'd0;

    else if(!stall && !sleep_mode)
        pc_out <= pc_out + 1'b1;

end

endmodule

rtl/register_file.v
`timescale 1ns/1ps

module register_file(

    input clk,
    input we,

    input [1:0] rs1,
    input [1:0] rs2,
    input [1:0] rd,

    input [7:0] write_data,

    output [7:0] read_data1,
    output [7:0] read_data2,

    output [7:0] debug_r0,
    output [7:0] debug_r1,
    output [7:0] debug_r2,
    output [7:0] debug_r3

);

reg [7:0] regfile [0:3];

assign read_data1 = regfile[rs1];
assign read_data2 = regfile[rs2];

assign debug_r0 = regfile[0];
assign debug_r1 = regfile[1];
assign debug_r2 = regfile[2];
assign debug_r3 = regfile[3];

always @(posedge clk)
begin
    if(we)
        regfile[rd] <= write_data;
end

initial begin
    regfile[0] = 8'd2;
    regfile[1] = 8'd3;
    regfile[2] = 8'd4;
    regfile[3] = 8'd5;
end

endmodule

rtl/cpu_top.v
`timescale 1ns/1ps

module cpu_top(

    input clk,
    input rst,
    input wake_up,

    output [3:0]  debug_pc,
    output [15:0] debug_instruction,
    output        debug_stall,
    output        debug_sleep_mode,

    output [7:0] debug_r0_out,
    output [7:0] debug_r1_out,
    output [7:0] debug_r2_out,
    output [7:0] debug_r3_out,

output [1:0] debug_rs1,
output [1:0] debug_rs2,
output [1:0] debug_ex_rd

);

wire [3:0] pc_out;
wire [15:0] instruction;

wire stall;


wire sleep_mode;

wire reg_write;
wire mem_read;
wire mem_write;
wire sleep;
wire [1:0] rd;
wire [7:0] write_data;
wire we;

wire [3:0] opcode;

wire [1:0] rs1;
wire [1:0] rs2;
wire [1:0] ex_rd;

assign rs1 = pc_out[1:0];
assign rs2 = 2'b00;

assign ex_rd =
    pc_out[0] ?
    pc_out[1:0] :
    2'b11;

// Register file debug wires
wire [7:0] debug_r0;
wire [7:0] debug_r1;
wire [7:0] debug_r2;
wire [7:0] debug_r3;




assign opcode = instruction[15:12];

// Debug outputs
assign debug_pc          = pc_out;
assign debug_instruction = instruction;
assign stall = 1'b0;
assign debug_sleep_mode  = sleep_mode;

assign debug_r0_out = debug_r0;
assign debug_r1_out = debug_r1;
assign debug_r2_out = debug_r2;
assign debug_r3_out = debug_r3;

assign debug_rs1   = rs1;
assign debug_rs2   = rs2;
assign debug_ex_rd = ex_rd;

assign we = 1'b1;

assign rd = pc_out[1:0];

assign write_data = {4'b0000, pc_out};
// =================================================
// Register File
// =================================================

register_file rf(

    .clk(clk),
    .we(we),
.rd(rd),
.write_data(write_data),
    .rs1(2'b00),
    .rs2(2'b01),
    

    

    .read_data1(),
    .read_data2(),

    .debug_r0(debug_r0),
    .debug_r1(debug_r1),
    .debug_r2(debug_r2),
    .debug_r3(debug_r3)

);

// =================================================
// Program Counter
// =================================================

pc pc0(

    .clk(clk),
    .rst(rst),
    .stall(stall),
    .sleep_mode(sleep_mode),
    .pc_out(pc_out)

);

// =================================================
// Instruction Memory
// =================================================

instruction_memory imem(

    .address(pc_out),
    .instruction(instruction)

);

// =================================================
// Control Unit
// =================================================

control_unit cu(

    .opcode(opcode),

    .reg_write(reg_write),
    .mem_read(mem_read),
    .mem_write(mem_write),

    .alu_src(),

    .sleep(sleep)

);

// =================================================
// Sleep Controller
// =================================================

sleep_controller sc(

    .clk(clk),
    .rst(rst),

    .sleep_instruction(sleep),

    .wake_up(wake_up),

    .sleep_mode(sleep_mode)

);

//Hazard Detection
endmodule

tb/cpu_tb.v
`timescale 1ns/1ps

module cpu_tb;

reg clk;
reg rst;
reg wake_up;

cpu_top uut(
    .clk(clk),
    .rst(rst),
    .wake_up(wake_up)
);

// Clock
initial begin
    clk = 0;
    forever #5 clk = ~clk;
end

// VCD
initial begin
    $dumpfile("cpu.vcd");
    $dumpvars(0,cpu_tb);
end

// Stimulus
initial begin

    rst = 1;
    wake_up = 0;

    #20;
    rst = 0;

    #100;

    wake_up = 1;
    #10;
    wake_up = 0;

    #200;

    $finish;

end

// Main Monitor
initial begin

$display("TIME\tPC\tINSTR\tSTALL\tSLEEP");

$monitor("%0t\t%0d\t%h\t%b\t%b",
         $time,
         uut.debug_pc,
         uut.debug_instruction,
         uut.debug_stall,
         uut.debug_sleep_mode);

end

// Register Monitor
always @(posedge clk)
begin

$display(
"T=%0t | R0=%0d R1=%0d R2=%0d R3=%0d ACC=%0d",
$time,

uut.debug_pc,
uut.debug_instruction,
uut.debug_stall,
uut.debug_sleep_mode,
uut.debug_pc,
uut.debug_rs1,
uut.debug_rs2,
uut.debug_ex_rd,
uut.debug_stall
);

end

endmodule

cpu.vcd
$date
	Wed Jun 10 15:16:53 2026
$end
$version
	Icarus Verilog
$end
$timescale
	1ps
$end
$scope module cpu_tb $end
$var reg 1 ! clk $end
$var reg 1 " rst $end
$var reg 1 # wake_up $end
$scope module uut $end
$var wire 1 $ clk $end
$var wire 2 % debug_ex_rd [1:0] $end
$var wire 16 & debug_instruction [15:0] $end
$var wire 4 ' debug_pc [3:0] $end
$var wire 8 ( debug_r0 [7:0] $end
$var wire 8 ) debug_r0_out [7:0] $end
$var wire 8 * debug_r1 [7:0] $end
$var wire 8 + debug_r1_out [7:0] $end
$var wire 8 , debug_r2 [7:0] $end
$var wire 8 - debug_r2_out [7:0] $end
$var wire 8 . debug_r3 [7:0] $end
$var wire 8 / debug_r3_out [7:0] $end
$var wire 2 0 debug_rs1 [1:0] $end
$var wire 2 1 debug_rs2 [1:0] $end
$var wire 1 2 debug_sleep_mode $end
$var wire 1 3 debug_stall $end
$var wire 2 4 ex_rd [1:0] $end
$var wire 16 5 instruction [15:0] $end
$var wire 1 6 mem_read $end
$var wire 1 7 mem_write $end
$var wire 4 8 opcode [3:0] $end
$var wire 4 9 pc_out [3:0] $end
$var wire 2 : rd [1:0] $end
$var wire 1 ; reg_write $end
$var wire 2 < rs1 [1:0] $end
$var wire 2 = rs2 [1:0] $end
$var wire 1 > rst $end
$var wire 1 ? sleep $end
$var wire 1 @ sleep_mode $end
$var wire 1 A stall $end
$var wire 1 B wake_up $end
$var wire 1 C we $end
$var wire 8 D write_data [7:0] $end
$scope module rf $end
$var wire 1 $ clk $end
$var wire 8 E debug_r0 [7:0] $end
$var wire 8 F debug_r1 [7:0] $end
$var wire 8 G debug_r2 [7:0] $end
$var wire 8 H debug_r3 [7:0] $end
$var wire 2 I rd [1:0] $end
$var wire 8 J read_data1 [7:0] $end
$var wire 8 K read_data2 [7:0] $end
$var wire 2 L rs1 [1:0] $end
$var wire 2 M rs2 [1:0] $end
$var wire 1 C we $end
$var wire 8 N write_data [7:0] $end
$upscope $end
$scope module pc0 $end
$var wire 1 $ clk $end
$var wire 1 > rst $end
$var wire 1 @ sleep_mode $end
$var wire 1 A stall $end
$var reg 4 O pc_out [3:0] $end
$upscope $end
$scope module imem $end
$var wire 4 P address [3:0] $end
$var wire 16 Q instruction [15:0] $end
$upscope $end
$scope module cu $end
$var wire 4 R opcode [3:0] $end
$var reg 1 S alu_src $end
$var reg 1 T mem_read $end
$var reg 1 U mem_write $end
$var reg 1 V reg_write $end
$var reg 1 W sleep $end
$upscope $end
$scope module sc $end
$var wire 1 $ clk $end
$var wire 1 > rst $end
$var wire 1 ? sleep_instruction $end
$var wire 1 B wake_up $end
$var reg 1 X sleep_mode $end
$upscope $end
$upscope $end
$upscope $end
$enddefinitions $end
#0
$dumpvars
0X
0W
1V
0U
0T
0S
b0 R
b110000000 Q
b0 P
b0 O
b0 N
b1 M
b0 L
b11 K
b10 J
b0 I
b101 H
b100 G
b11 F
b10 E
b0 D
1C
0B
0A
0@
0?
1>
b0 =
b0 <
1;
b0 :
b0 9
b0 8
07
06
b110000000 5
b11 4
z3
02
b0 1
b0 0
b101 /
b101 .
b100 -
b100 ,
b11 +
b11 *
b10 )
b10 (
b0 '
b110000000 &
b11 %
0$
0#
1"
0!
$end
#5000
b0 J
b0 )
b0 (
b0 E
1!
1$
#10000
0!
0$
#15000
1!
1$
#20000
0!
0$
0"
0>
#25000
1V
1;
b1 4
b1 %
b1 8
b1 R
b1 :
b1 I
b1 <
b1 0
b1 O
b1011011000000 5
b1011011000000 Q
b1011011000000 &
b1 D
b1 N
b1 9
b1 P
b1 '
1!
1$
#30000
0!
0$
#35000
1V
1;
b11 4
b11 %
b111 8
b111 R
b10 :
b10 I
b10 <
b10 0
b10 O
b111000110000000 5
b111000110000000 Q
b111000110000000 &
b10 D
b10 N
b10 9
b10 P
b10 '
b1 K
b1 +
b1 *
b1 F
1!
1$
#40000
0!
0$
#45000
1W
1?
0V
0;
b1001 8
b1001 R
b11 :
b11 I
b11 <
b11 0
b11 O
b1001000000000000 5
b1001000000000000 Q
b1001000000000000 &
b11 D
b11 N
b11 9
b11 P
b11 '
b10 -
b10 ,
b10 G
1!
1$
#50000
0!
0$
#55000
0W
0?
b1111 8
b1111 R
b0 :
b0 I
b0 <
b0 0
b100 O
b1111000000000000 5
b1111000000000000 Q
b1111000000000000 &
b100 D
b100 N
b100 9
b100 P
b100 '
1X
1@
12
b11 /
b11 .
b11 H
1!
1$
#60000
0!
0$
#65000
b100 J
b100 )
b100 (
b100 E
1!
1$
#70000
0!
0$
#75000
1!
1$
#80000
0!
0$
#85000
1!
1$
#90000
0!
0$
#95000
1!
1$
#100000
0!
0$
#105000
1!
1$
#110000
0!
0$
#115000
1!
1$
#120000
0!
0$
1#
1B
#125000
0X
0@
02
1!
1$
#130000
0!
0$
0#
0B
#135000
b1 4
b1 %
bx 8
bx R
b1 :
b1 I
b1 <
b1 0
b101 O
bx 5
bx Q
bx &
b101 D
b101 N
b101 9
b101 P
b101 '
1!
1$
#140000
0!
0$
#145000
b11 4
b11 %
b10 :
b10 I
b10 <
b10 0
b110 O
b110 D
b110 N
b110 9
b110 P
b110 '
b101 K
b101 +
b101 *
b101 F
1!
1$
#150000
0!
0$
#155000
b11 :
b11 I
b11 <
b11 0
b111 O
b111 D
b111 N
b111 9
b111 P
b111 '
b110 -
b110 ,
b110 G
1!
1$
#160000
0!
0$
#165000
b0 :
b0 I
b0 <
b0 0
b1000 O
b1000 D
b1000 N
b1000 9
b1000 P
b1000 '
b111 /
b111 .
b111 H
1!
1$
#170000
0!
0$
#175000
b1 4
b1 %
b1 :
b1 I
b1 <
b1 0
b1001 O
b1001 D
b1001 N
b1001 9
b1001 P
b1001 '
b1000 J
b1000 )
b1000 (
b1000 E
1!
1$
#180000
0!
0$
#185000
b11 4
b11 %
b10 :
b10 I
b10 <
b10 0
b1010 O
b1010 D
b1010 N
b1010 9
b1010 P
b1010 '
b1001 K
b1001 +
b1001 *
b1001 F
1!
1$
#190000
0!
0$
#195000
b11 :
b11 I
b11 <
b11 0
b1011 O
b1011 D
b1011 N
b1011 9
b1011 P
b1011 '
b1010 -
b1010 ,
b1010 G
1!
1$
#200000
0!
0$
#205000
b0 :
b0 I
b0 <
b0 0
b1100 O
b1100 D
b1100 N
b1100 9
b1100 P
b1100 '
b1011 /
b1011 .
b1011 H
1!
1$
#210000
0!
0$
#215000
b1 4
b1 %
b1 :
b1 I
b1 <
b1 0
b1101 O
b1101 D
b1101 N
b1101 9
b1101 P
b1101 '
b1100 J
b1100 )
b1100 (
b1100 E
1!
1$
#220000
0!
0$
#225000
b11 4
b11 %
b10 :
b10 I
b10 <
b10 0
b1110 O
b1110 D
b1110 N
b1110 9
b1110 P
b1110 '
b1101 K
b1101 +
b1101 *
b1101 F
1!
1$
#230000
0!
0$
#235000
b11 :
b11 I
b11 <
b11 0
b1111 O
b1111 D
b1111 N
b1111 9
b1111 P
b1111 '
b1110 -
b1110 ,
b1110 G
1!
1$
#240000
0!
0$
#245000
1V
1;
b0 8
b0 R
b0 :
b0 I
b0 <
b0 0
b0 O
b110000000 5
b110000000 Q
b110000000 &
b0 D
b0 N
b0 9
b0 P
b0 '
b1111 /
b1111 .
b1111 H
1!
1$
#250000
0!
0$
#255000
1V
1;
b1 4
b1 %
b1 8
b1 R
b1 :
b1 I
b1 <
b1 0
b1 O
b1011011000000 5
b1011011000000 Q
b1011011000000 &
b1 D
b1 N
b1 9
b1 P
b1 '
b0 J
b0 )
b0 (
b0 E
1!
1$
#260000
0!
0$
#265000
1V
1;
b11 4
b11 %
b111 8
b111 R
b10 :
b10 I
b10 <
b10 0
b10 O
b111000110000000 5
b111000110000000 Q
b111000110000000 &
b10 D
b10 N
b10 9
b10 P
b10 '
b1 K
b1 +
b1 *
b1 F
1!
1$
#270000
0!
0$
#275000
1W
1?
0V
0;
b1001 8
b1001 R
b11 :
b11 I
b11 <
b11 0
b11 O
b1001000000000000 5
b1001000000000000 Q
b1001000000000000 &
b11 D
b11 N
b11 9
b11 P
b11 '
b10 -
b10 ,
b10 G
1!
1$
#280000
0!
0$
#285000
0W
0?
b1111 8
b1111 R
b0 :
b0 I
b0 <
b0 0
1X
1@
12
b100 O
b1111000000000000 5
b1111000000000000 Q
b1111000000000000 &
b100 D
b100 N
b100 9
b100 P
b100 '
b11 /
b11 .
b11 H
1!
1$
#290000
0!
0$
#295000
b100 J
b100 )
b100 (
b100 E
1!
1$
